projen/canary_package/__init__.py
projen/canary_package/py.typed
projen/canary_package/_jsii/__init__.py
projen/canary_package/_jsii/canary-package@0.0.17.jsii.tgz
projen_canary_package-0.0.17.dist-info/LICENSE
projen_canary_package-0.0.17.dist-info/METADATA
projen_canary_package-0.0.17.dist-info/WHEEL
projen_canary_package-0.0.17.dist-info/top_level.txt
projen_canary_package-0.0.17.dist-info/RECORD
